erp_data_model/__init__.py
erp_data_model/base.py
erp_data_model/catalog.py
erp_data_model-0.0.1.dist-info/LICENSE
erp_data_model-0.0.1.dist-info/METADATA
erp_data_model-0.0.1.dist-info/WHEEL
erp_data_model-0.0.1.dist-info/top_level.txt
erp_data_model-0.0.1.dist-info/RECORD
