Metadata-Version: 2.1
Name: erp-data-model
Version: 0.0.1
Summary: ERP data model: pydantic data model for ERP
Home-page: https://github.com/spochic/erp-data-model
Author: Sebastien Pochic
Author-email: spochic@gmail.com
Project-URL: Bug Tracker, https://github.com/spochic/erp-data-model/issues
Classifier: Programming Language :: Python :: 3
Classifier: License :: OSI Approved :: MIT License
Classifier: Operating System :: OS Independent
Classifier: Development Status :: 3 - Alpha
Classifier: Topic :: Database :: Front-Ends
Requires-Python: >=3.10
License-File: LICENSE
